<?xml version="1.0" encoding="utf-8"?>
<Tests xmlns="vtfSchema">

<Test name="testHBD03_HybridStreamCheck">

<Default> 
<TestVariables>
<String name="alignmentMode">powerOfTwo</String>
<String name="readWriteSelect">write</String>
<String name="transferLengthMode">random</String>
<Int32 name="verifyMode">0</Int32>
<String name="amountOfData">upTo5GB</String>
</TestVariables> 
</Default>

<Variation name="aligned" skip="false">  
<TestVariablesOverride> 
<String name="alignmentMode">sectorAligned</String>
<String name="readWriteSelect">write</String>
<String name="transferLengthMode">random</String>
<Int32 name="verifyMode">2</Int32>
<String name="amountOfData">upTo5GB</String>
</TestVariablesOverride> 
</Variation>

</Test>
</Tests>